README.md
setup.py
azs/__init__.py
azs/azs.py
azs.egg-info/PKG-INFO
azs.egg-info/SOURCES.txt
azs.egg-info/dependency_links.txt
azs.egg-info/requires.txt
azs.egg-info/top_level.txt