Metadata-Version: 2.1
Name: azs
Version: 1.0.3
Summary: Scraper for Amazon
Home-page: https://github.com/Harkame/AmaZonScraper
Author: Harkame
Classifier: Programming Language :: Python
Classifier: License :: OSI Approved
Classifier: Operating System :: OS Independent
Requires-Python: >=3.6
